{
  "comment": "Из условия видим, что для рябины характерен листопад, так как его листья меняют окраску (1), имеет плоды, поэтому цветковое растение (5), является деревом, поэтому имеет один одревесневший стебель (6).",
  "difficulty": 3,
  "exam_topic": {
    "id": 2921,
    "title": "Покрытосеменные и голосеменные"
  },
  "id": 27985,
  "is_obsolete": false,
  "number": 7,
  "source": null,
  "subject": {
    "color": "#000000",
    "id": 66,
    "task_count": 0,
    "title": "Биология ОГЭ"
  },
  "task_question": {
    "Val": {
      "answers": [
        {
          "answer": "156",
          "points": 2
        }
      ],
      "comment": "",
      "description": "Рябина обыкновенная является деревом со сложными листьями, изменяющими окраску и опадающими осенью, и с сочными плодами, собранными в гроздья.\nИспользуя эти сведения, выберите из приведённого ниже списка три утверждения, относящихся к описанию данных признаков этого растения . Запишите в таблицу цифры, соответствующие выбранным ответам.\n\n1) Для рябины характерен листопад.\n2) Опыление рябины перекрёстное насекомыми.\n3) Плодами рябины питаются зимующие птицы.\n4) Плоды рябины - яблоки.\n5) Рябина - цветковое растение.\n6) У рябины единственный одревесневший стебель.",
      "error_conditions": [],
      "id": 247624,
      "is_case_insensitive": false,
      "is_strict_order": false,
      "order_id": 7,
      "points": 2,
      "type_id": "writing_words",
      "video_link": null
    },
    "Valid": true
  },
  "time_seconds": 0,
  "topic": null,
  "video_link": null
}
