{
  "comment": "А - Телецкое озеро располагается в Республике Алтай\nБ - Чукотский АО располагается в двух частях света",
  "difficulty": 3,
  "exam_topic": {
    "id": 2977,
    "title": "6.5 Регионы России"
  },
  "id": 29294,
  "is_obsolete": false,
  "number": 20,
  "source": null,
  "subject": {
    "color": "#000000",
    "id": 68,
    "task_count": 0,
    "title": "География ОГЭ"
  },
  "task_question": {
    "Val": {
      "answers": [
        {
          "answer": "42",
          "points": 1
        }
      ],
      "comment": "",
      "description": "Туристические фирмы разных регионов России разработали слоганы (рекламные лозунги) для привлечения туристов. Установите соответствие между слоганами и регионами: к каждому элементу первого столбца подберите соответствующий элемент из второго столбца.\nСЛОГАНЫ РЕГИОНЫА) Добро пожаловать на уникальное Телецкое озеро!\nБ) Здесь можно побывать в Западном\nи Восточном полушариях!\n1) Мурманская область\n2) Чукотский АО\n3) Приморский край\n4) Республика Алтай",
      "error_conditions": [],
      "id": 248933,
      "is_case_insensitive": false,
      "is_strict_order": false,
      "order_id": 20,
      "points": 1,
      "type_id": "writing_words",
      "video_link": null
    },
    "Valid": true
  },
  "time_seconds": 0,
  "topic": null,
  "video_link": null
}
