{
  "comment": "Решение:\n1) Воспользуемся поисковыми средствами текстового редактора. Найдем начало IV главы в повести, для этого в MS Word в меню \"Главная\" - \"Найти и заменить\" вводим римскую цифру \"IV\" и выделяем весь текст необходимой главы.\n2) Копируем выделенный фрагмент на новый лист, для чего нажимаем правую кнопку мыши, выбираем пункт \"Копировать\". Создаем новый документ и вставляем IV главу.\n3) Найдем все вхождения слова \"не\" со строчной буквы, для чего в MS Word в меню \"Главная\" - \"Найти и заменить\" вводим слово \"не\", ставим галки \"Учитывать регистр\", \"Только слово целиком\" и выбираем \"Выделение при чтении\" - \"Выделить все\". Находим 47 вхождения необходимого сочетания букв.",
  "difficulty": 0,
  "exam_topic": {
    "id": 2717,
    "title": "№10 Редактор текста"
  },
  "id": 23781,
  "is_obsolete": false,
  "number": 10,
  "source": null,
  "subject": {
    "color": "#000000",
    "id": 20,
    "task_count": 0,
    "title": "Информатика"
  },
  "task_question": {
    "Val": {
      "answers": [
        {
          "answer": "47",
          "points": 1
        }
      ],
      "comment": "",
      "description": "ID Задания: REZ2310_02\n(РЕЗЕРВ 2023) 0025028311\nС помощью текстового редактора определите, сколько раз, встречается слово «не» со строчной буквы в тексте IV главы повести А.И. Куприна «Поединок». Другие слова, содержащие сочетание букв «не», такие как «нет» и т.д., учитывать не следует. В ответе укажите только число.\nФайл к заданию: KIM_0015973095_10.doc\nhttps://docs.google.com/document/d/1y8PM6AXd97UX-NFcJkz6ZHfuLKxLhU4C/edit",
      "error_conditions": [],
      "id": 243500,
      "is_case_insensitive": false,
      "is_strict_order": false,
      "order_id": 5,
      "points": 1,
      "type_id": "writing_words",
      "video_link": null
    },
    "Valid": true
  },
  "time_seconds": 180,
  "topic": {
    "id": 29,
    "title": "Редактор текста"
  },
  "video_link": null
}
