{
  "comment": "А) \\(SO_{2} + 2H_{2}S → 3S + 2H_{2}O\\) - при взаимодействии оксида серы IV и сероводорода образуется сера и вода (ОВР, сера - и восстановитель (\\(S^{-2}→S^{0}\\)), и окислитель (\\(S^{+2}→S^{0}\\))\nБ) \\(2H_{2}S + 3O_{2} (изб.) → 2SO_{2} + 2H_{2}O\\) - при взаимодействии сероводорода и кислорода образуется оксид серы IV и вода (ОВР, сера - восстановитель (\\(S^{-2}→S^{0}\\)), кислород - окислитель (\\(O_{2}^{0} → 2O^{-2}\\)), водород не изменяет свою СО, поэтому образуется вода)\nВ) \\(2SO_{2} + O_{2} → 2SO_{3}\\) - при взаимодействии оксида серы IV и кислорода образуется оксид серы VI (реакция соединения)",
  "difficulty": 3,
  "exam_topic": {
    "id": 2889,
    "title": "Химические свойства простых и сложных веществ"
  },
  "id": 35797,
  "is_obsolete": false,
  "number": 9,
  "source": null,
  "subject": {
    "color": "#000000",
    "id": 65,
    "task_count": 0,
    "title": "Химия ОГЭ"
  },
  "task_question": {
    "Val": {
      "answers": [
        {
          "answer": "523",
          "points": 2
        }
      ],
      "comment": "",
      "description": "Установите соответствие между реагирующими веществами и продуктами их взаимодействия: к каждой позиции, обозначенной буквой, подберите соответствующую позицию, обозначенную цифрой.\nРЕАГИРУЮЩИЕ ВЕЩЕСТВАПРОДУКТ(Ы) ВЗАИМОДЕЙСТВИЯА) \\(SO_{2} + H_{2}S →\\)1) \\(→SO_{2} + H_{2}\\)Б) \\(H_{2}S + O_{2} (изб.) →\\)2) \\(→SO_{2} + H_{2}O\\)В) \\(SO_{2} + O_{2}→\\)3) \\(→SO_{3}\\) 4) \\(→SO_{3} + H_{2}O\\) 5) \\(→S + H_{2}O\\)Запишите в таблицу выбранные цифры под соответствующими буквами.",
      "error_conditions": [],
      "id": 255436,
      "is_case_insensitive": false,
      "is_strict_order": false,
      "order_id": 9,
      "points": 2,
      "type_id": "writing_words",
      "video_link": null
    },
    "Valid": true
  },
  "time_seconds": 0,
  "topic": null,
  "video_link": null
}
