{
  "comment": "",
  "difficulty": 3,
  "exam_topic": {
    "id": 2912,
    "title": "Методы биологии"
  },
  "id": 27746,
  "is_obsolete": false,
  "number": 4,
  "source": null,
  "subject": {
    "color": "#000000",
    "id": 66,
    "task_count": 0,
    "title": "Биология ОГЭ"
  },
  "task_question": {
    "Val": {
      "answers": [
        {
          "answer": "15",
          "points": 2
        }
      ],
      "comment": "",
      "description": "Изучите график зависимости использования организмом человека энергии гликогена от продолжительности физической нагрузки (по оси х отложена продолжительность физической нагрузки (мин.), а по оси у — доля использования гликогена от других источников энергии в клетке (%)).\nКакие два из приведённых ниже описаний характеризуют данную зависимость?\n\nДоля использованного гликогена\n1) снижается на всём протяжении измерений\n2) имеет минимум на 20-й минуте тренировки\n3) не меняется с 10-й по 15-ю минуту тренировки\n4) составляет 10 % к 35-й минуте тренировки\n5) изменяется линейно с 5-й по 8-ю минуту тренировки",
      "error_conditions": [],
      "id": 247385,
      "is_case_insensitive": false,
      "is_strict_order": false,
      "order_id": 4,
      "points": 2,
      "type_id": "writing_words",
      "video_link": null
    },
    "Valid": true
  },
  "time_seconds": 0,
  "topic": null,
  "video_link": null
}
