{
  "comment": "Так как треугольник равнобедренный, то его углы при основании равны, следовательно, равны и их синусы:\n$$\\sin BAC=\\sin ABC$$\nРассмотрим \\(\\Delta ABH\\):\n$$\\sin ABC=\\sin ABH=\\frac{AH}{AB}=\\frac{4}{5}=0,8$$\nОтвет: 0,8",
  "difficulty": 0,
  "exam_topic": {
    "id": 2372,
    "title": "1.1 Тригонометрия в прямоугольном треугольнике"
  },
  "id": 5028,
  "is_obsolete": false,
  "number": 1,
  "source": null,
  "subject": {
    "color": "#000000",
    "id": 19,
    "task_count": 0,
    "title": "Профильная математика"
  },
  "task_question": {
    "Val": {
      "answers": [
        {
          "answer": "0,8",
          "points": 1
        }
      ],
      "comment": "",
      "description": "В треугольнике \\(ABC~AC=BC, AB=5,\\) высота \\(AH\\) равна \\(4\\). Найдите синус угла \\(BAC\\).",
      "error_conditions": [],
      "id": 70268,
      "is_case_insensitive": false,
      "is_strict_order": false,
      "order_id": 1,
      "points": 1,
      "type_id": "writing_words",
      "video_link": "https://www.youtube.com/embed/3Lrx3ZVzLyc?start=2177"
    },
    "Valid": true
  },
  "time_seconds": 1800,
  "topic": {
    "id": 1,
    "title": "Простейшая планиметрия"
  },
  "video_link": "https://www.youtube.com/embed/3Lrx3ZVzLyc?start=2177"
}
