{
  "comment": "",
  "difficulty": 0,
  "exam_topic": {
    "id": 915,
    "title": "Средства связи предложений в тексте"
  },
  "id": 21616,
  "is_obsolete": false,
  "number": 1,
  "source": null,
  "subject": {
    "color": "#000000",
    "id": 2,
    "task_count": 0,
    "title": "Русский язык"
  },
  "task_question": {
    "Val": {
      "answers": [
        {
          "answer": "каждый",
          "points": 1
        },
        {
          "answer": "любой",
          "points": 1
        },
        {
          "answer": "всякий",
          "points": 1
        }
      ],
      "comment": "",
      "description": "Прочитайте текст и выполните задание.\n\nОставляя пока в стороне все материальные выгоды, которые мы получаем от науки, обратим внимание на ту её сторону, которая доставляет нам внутреннее удовлетворение и служит главной причиной нашего духовного развития. Цель изучения наук и переработки тех сведений, которые они доставляют, есть формирование в нас личности, именно личности, то есть совокупности таких идей и убеждений, которые бы составили собой неотъемлемую принадлежность нашего «я». <...> человек представляет собой независимое и обособленное целое.\n\nБыть цельным, быть самостоятельной единицей, то есть иметь своё действительно своим, – идеал образованного и культурного человека. Но приобрести убеждения, которые бы образовали в нас личность, можно лишь путём долгого и упорного изучения наук. Имея свои убеждения, мы становимся в определённое отношение к окружающим людям, обществу, государству, и это уже должно доставить нам большое удовлетворение. Да, кроме того, одно чистое знание без всякого употребления его на выработку миросозерцания уже служит для человека источником высоких наслаждений.\n\nВыгоду образования можно сравнить с урожаем на земле крестьянина. Ранней весной он начинает свои полевые работы и трудится всё лето, несмотря на страшно изнуряющую жару, в поле, где нет ни одного дерева, которое бы могло скрыть его под свою тень. Но честно потрудившегося крестьянина ожидает удовольствие отдыха и полного материального достатка на круглый год.\n\n(По А.Ф. Лосеву)\n\nЗадание 1. Самостоятельно подберите определительное местоимение, которое должно стоять на месте пропуска в первом (1) абзаце текста. Запишите это местоимение.",
      "error_conditions": [],
      "id": 241383,
      "is_case_insensitive": false,
      "is_strict_order": false,
      "order_id": 25,
      "points": 1,
      "type_id": "writing_words",
      "video_link": null
    },
    "Valid": true
  },
  "time_seconds": 0,
  "topic": null,
  "video_link": null
}
