{
  "comment": "Постоянные издержки не зависят от объема производства и выплачиваются регулярно в одинаковом размере, переменные издержки зависят от объема производства\nА) это постоянная издержка\nБ) это переменная издержка, так как как для производства разного объема продукции нужен разный объем сырья\nВ) это постоянная издержка\nГ) это переменная издержка, так как зависит от того, сколько работник произведет продукта (или выполнит работ) в определенный срок\nД) это постоянная издержка",
  "difficulty": 0,
  "exam_topic": {
    "id": 2557,
    "title": "Предприятие (фирма) в экономике. Издержки, их виды. Выручка, прибыль"
  },
  "id": 26461,
  "is_obsolete": false,
  "number": 6,
  "source": null,
  "subject": {
    "color": "#000000",
    "id": 21,
    "task_count": 0,
    "title": "Обществознание"
  },
  "task_question": {
    "Val": {
      "answers": [
        {
          "answer": "12121",
          "points": 2
        }
      ],
      "comment": "",
      "description": "Установите соответствие между примерами и видами издержек фирмы в краткосрочном периоде: к каждой позиции, данной в первом столбце, подберите соответствующую позицию из второго столбца.\n\nПРИМЕРЫВИДЫ ИЗДЕРЖЕКA) страховые выплаты\nБ) приобретение сырья\nB) оплата процентов по банковским кредитам\nГ) сдельная оплата труда наёмных работников\nД) арендная плата за помещение\n1) постоянные\n2) переменные\n\nЗапишите в таблицу выбранные цифры под соответствующими буквами.",
      "error_conditions": [],
      "id": 246100,
      "is_case_insensitive": false,
      "is_strict_order": false,
      "order_id": 6,
      "points": 2,
      "type_id": "writing_words",
      "video_link": "https://www.youtube.com/live/IWl4rURAMyk?si=1ox0lgsqcjnwFr-O&t=4851"
    },
    "Valid": true
  },
  "time_seconds": 0,
  "topic": null,
  "video_link": "https://www.youtube.com/live/IWl4rURAMyk?si=1ox0lgsqcjnwFr-O&t=4851"
}
