{
  "comment": "техничный - обладающий высокой техникой, мастерством (техничный спортсмен)\nтехнический - относящийся к технике, используемый\nв промышленности (технический институт, технические масла)",
  "difficulty": 0,
  "exam_topic": {
    "id": 912,
    "title": "Употребление паронимов"
  },
  "id": 11961,
  "is_obsolete": false,
  "number": 5,
  "source": null,
  "subject": {
    "color": "#000000",
    "id": 2,
    "task_count": 0,
    "title": "Русский язык"
  },
  "task_question": {
    "Val": {
      "answers": [
        {
          "answer": "техничная",
          "points": 1
        }
      ],
      "comment": "",
      "description": "В одном из приведённых ниже предложений НЕВЕРНО употреблено выделенное слово. Исправьте лексическую ошибку, подобрав к выделенному слову пароним. Запишите подобранное слово.\n\nТе критики, которые не могли понять и оценить ВЕЛИКИЕ заслуги Пушкина, стремились принизить творчество гения, обвиняя его в грубости, «простонародности».\nФорвард забросил две шайбы и сделал одну результативную ПЕРЕДАЧУ.\nАктриса, исполнявшая в спектакле ведущую роль, приветствовала зрителей ЦАРСТВЕННЫМ наклоном головы.\nМы познакомились с Елизаветой Петровной – тихой и БЕЗОТВЕТНОЙ старушкой лет восьмидесяти.\nСпециалисты уверены, что ТЕХНИЧЕСКАЯ спортивная команда, в составе которой игроки только высокого уровня, станет призёром чемпионата.",
      "error_conditions": [],
      "id": 151869,
      "is_case_insensitive": false,
      "is_strict_order": false,
      "order_id": 30,
      "points": 1,
      "type_id": "writing_words",
      "video_link": null
    },
    "Valid": true
  },
  "time_seconds": 2013,
  "topic": null,
  "video_link": null
}
