{
  "comment": "Ответ:\n1. Независимая переменная – концентрация этилена, зависимая – характер созревания плодов.\n2. Нулевая гипотеза: этилен не влияет на характер созревания плодов.\n3. Замкнутое пространство необходимо для поддержания концентрации этилена на постоянном уровне.\n4. Если пространство не будет герметичным, то концентрация этилена не будет постоянной, а это повлияет на результаты эксперимента.",
  "difficulty": 0,
  "exam_topic": {
    "id": 2525,
    "title": "Царство Растения. Строение и жизнедеятельность растений"
  },
  "id": 8320,
  "is_obsolete": false,
  "number": 22,
  "source": null,
  "subject": {
    "color": "#000000",
    "id": 10,
    "task_count": 0,
    "title": "Биология"
  },
  "task_question": {
    "Val": {
      "answers": null,
      "comment": "",
      "description": "Ученый изучал влияние фитогормонов на скорость созревания плодов бананов. В своем эксперименте исследователь в замкнутом пространстве обрабатывал плоды этиленом и оценивал его внешнее состояние через 3 суток. На рисунке представлена схема опыта, цифрами указана концентрация этилена в миллионных долях.\nКакая переменная независимая (задаваемая), а какая зависимая (изменяющаяся)? Какую нулевую смог сформулировать исследователь перед постановкой эксперимента? Как этилен влияет на характер созревания плодов? Объясните, почему для проведения опыта исследователь замкнутое пространство. Почему результаты эксперимента могут быть недостоверными, если пространство было не герметичным.\nНулевая гипотеза – принимаемое по умолчанию предположение, что не существует связи между двумя событиями, феноменами",
      "error_conditions": null,
      "id": 102005,
      "is_case_insensitive": false,
      "is_strict_order": false,
      "order_id": 17,
      "points": 3,
      "type_id": "full_answer",
      "video_link": null
    },
    "Valid": true
  },
  "time_seconds": 1200,
  "topic": null,
  "video_link": "https://www.youtube.com/embed/BqYzREaBpHk"
}
