{
  "comment": "Английский парламент возник в ходе гражданской войны в период правления Генриха III в 1265 г. Таким образом, в Англии осуществился переход к новой, более централизованной форме феодального государства, к феодальной монархии с сословным представительством (парламентом)",
  "difficulty": 3,
  "exam_topic": {
    "id": 3106,
    "title": "16.1. История зарубежных стран. Древний мир, Средние века, Новое время"
  },
  "id": 32966,
  "is_obsolete": false,
  "number": 16,
  "source": null,
  "subject": {
    "color": "#000000",
    "id": 29,
    "task_count": 0,
    "title": "Истoрия ОГЭ"
  },
  "task_question": {
    "Val": {
      "answers": [
        {
          "answer": "2",
          "points": 1
        }
      ],
      "comment": "",
      "description": "1) ослабление и падение Западной Римской империи\n2) образование централизованного государства в Англии\n3) контрреформация в Европе\n4) война за независимость США\n\nВ ходе какого из перечисленных событий, процессов был впервые созван парламент? Укажите порядковый номер этого события или процесса.",
      "error_conditions": [],
      "id": 252605,
      "is_case_insensitive": false,
      "is_strict_order": false,
      "order_id": 16,
      "points": 1,
      "type_id": "writing_words",
      "video_link": null
    },
    "Valid": true
  },
  "time_seconds": 0,
  "topic": null,
  "video_link": null
}
